{
  "type": "forge:conditional",
  "recipes": [
    {
      "conditions": [
        {
          "type": "netherrocks:flag",
          "flag": "aesthetics_enabled"
        }
      ],
      "recipe": {
        "type": "minecraft:crafting_shaped",
        "key": {
          "S": {
            "item": "netherrocks:malachite_ingot"
          }
        },
        "pattern": [
          "SS",
          "SS"
        ],
        "result": {
          "item": "netherrocks:malachite_bricks"
        }
      }
    }
  ]
}